{
  "status": "complete",
  "ownerThreadId": "845ef83f-58fa-49ca-81ce-44a744e34e8f",
  "phases": [
    {
      "id": "phase-1",
      "title": "Foundation: App Shell, Navigation, Data Layer & Types",
      "description": "Create the entire app foundation. \n\n1. Write /frontend/pages/data/sampleData.ts — a comprehensive TypeScript data module exporting: demoRequests (typed array from the Demo tracker CSV with 50+ records including status: 'Reviewed'|'Canceled'|'Needs Review'|'DELETED'|'NEEDS REVIEW', geo: 'UK'|'US'|'JP'|'DE', type, requester, approver, organization (from guestsOrganization), host, date_requested, demo_date, start_time, end_time, vehicle_type, total_guests, total_vehicles, lead_days, readiness_date, slack_link, cancel_reason, channel, description), postDemoSessions (50+ records from Post Demo CSV with model, aux_model, vehicle_id, geo, demo_type, operator (submitter), route, weather, feature_rating, smoothness_rating, active_issues_list, uds_count, total_interventions, interventions object, model_behavior, driving_feature, comments, demo_datetime), operationFeedback (all records from Operation Feedback CSV with date, geo, operator, satisfaction_score, reported_issues, comments, feedback_host). Also export helper functions: normGeo(), normStatus(), leadBand(days: number) returning {key, label, color}, calcReadinessRate(), getDelayedOrders() (flags demos where lead_days < 3 as delayed). \n\n2. Write /frontend/pages/data/chartHelpers.ts — export aggregation helpers: aggregateDemosByMonth(), aggregateByGeo(), aggregateByType(), aggregateReadiness(), aggregateAvgSatisfaction(), aggregatePostDemoByModel(), aggregateInterventions(), aggregateIssues(). \n\n3. Write /frontend/components/AppShell.tsx — full sidebar layout. Left sidebar 240px wide (collapsible to 72px). Sidebar contains: brand logo area with 'Wayve Demo Ops' name, navigation items: Demo KPIs (/), Demo Tracker (/tracker), Demo Calendar (/calendar), Post Demo (/post-demo), Demo Cockpit (/cockpit), Demo Cost (/cost). Each nav item has icon (Lucide) + label. Active state highlighted in blue. Bottom: live sync status indicator (green dot + 'Live' text + last synced timestamp). Right side is scrollable content area. Sticky header bar inside content area with page title + filter controls. Use Tailwind CSS. Color scheme: background #F8FAFC, cards white, text #0F172A, muted #64748B, primary #2563EB. No dark mode needed but use semantic tokens where possible.\n\n4. Write /frontend/components/StatCard.tsx — KPI card with accent color top border, large number value, label, optional sub-label, hover lift animation.\n\n5. Write /frontend/components/DelayBadge.tsx — shows lead day band: 1-2 CRITICAL red #F20F31, 3-4 SHORT orange #F59E0B, 5-7 GOOD blue #0052FF, >7 EXCELLENT green #10B981, 0/null UNKNOWN gray.\n\n6. Write /frontend/components/GeoBadge.tsx — colored geo badge: UK blue, JP red, US green, DE orange.\n\n7. Write /frontend/components/StatusBadge.tsx — status chips: Reviewed green, Needs Review amber, Canceled red, DELETED gray.\n\n8. Finally write /frontend/App.tsx with BrowserRouter Routes for all 6 pages wrapped in AppShell.",
      "status": "complete",
      "notes": "All foundation files created. Data at /frontend/pages/data/sampleData.ts (55 demoRequests, 55 postDemoSessions, 24 operationFeedback + helper fns) and /frontend/pages/data/chartHelpers.ts (8 aggregation helpers + aggregateGeoTrend bonus). Components: AppShell (collapsible 240/72px sidebar, Zap brand icon, 6 nav items, live sync footer), StatCard, DelayBadge, GeoBadge, StatusBadge. Stub pages created for all 6 routes. App.tsx wires routes inside AppShell with useLocation-based page titles. No dark mode on these components per spec."
    },
    {
      "id": "phase-2",
      "title": "Demo KPIs Page: Executive Dashboard with Charts & Satisfaction Gauge",
      "description": "Build /frontend/pages/KPIPage.tsx — the executive overview dashboard.\n\nFilters row at top: Month select (Jan-Dec + ALL), Geo select (ALL/UK/JP/US/DE), Type select (dynamically populated). All filters are state-controlled and filter all charts/tables on page.\n\nSection 1 — KPI Cards row (6 cards): Total Demos, Total Guests, Approved Upcoming (demo_date >= today AND status=Reviewed), Cancelled count, Completion Rate (%), Avg Satisfaction Score (with 5 stars).\n\nSection 2 — 3-column grid:\n- Monthly Demo Trend: Recharts LineChart with gradient fill. Labels: month abbreviations. Show badge with total demo count.\n- Geo Distribution: Recharts DoughnutChart 70% cutout. Colors UK=#3B82F6, JP=#EF4444, US=#22C55E, DE=#F59E0B. Custom legend alongside with counts.\n- Demo Type Mix: DoughnutChart. VIP Demo=#AF52DE, External Guest=#3B82F6, Friends&Family=#22C55E, Candidate=#F59E0B, Internal=#22C55E, Recce/ST=#94A3B8.\n\nSection 3 — 2-column grid:\n- Pipeline Status: Stacked horizontal bar (Reviewed vs Needs Review vs Cancelled). Show completion rate at bottom.\n- Geo Trend: Multi-line Recharts LineChart. One line per geo (UK/JP/US/DE). Last 12 months.\n\nSection 4 — 3-column grid:\n- Geo At A Glance: 4 colored mini-cards (UK blue, JP red, US green, DE orange) each showing geo name, count, progress bar.\n- Demo Ops Satisfaction Gauge: Custom SVG semi-circle gauge. Use Recharts PieChart in semicircle mode (rotation:-90, circumference:180). 5 equal segments: red, orange, yellow, light-green, emerald. Needle drawn via Chart.js plugin equivalent using useRef canvas overlay. Center shows numeric score (e.g. 4.2). Render needle by drawing on a canvas overlay positioned absolutely above the Recharts chart.\n- Readiness Status: Stacked bar with 4 buckets (CRITICAL/SHORT/GOOD/EXCELLENT) + readiness rate below.\n\nSection 5 — Demo Feedback Details table (full width): Shows Date, Geo, Operator, Sat Score badge, Reported Issues, Comment, Host. Scrollable with sticky header. Data from operationFeedback filtered by current filters.\n\n⚠️ DELAY FLAG: Add a prominent banner/alert at top of page if any demos have lead_days < 3 (or are past due date without being completed). Use AlertTriangle icon with amber background. Show count of flagged demos with 'View in Tracker' link.\n\nData: Import from /frontend/pages/data/sampleData and /frontend/pages/data/chartHelpers.",
      "status": "complete",
      "notes": "KPI page complete. 3 files: /frontend/pages/KPIPage.tsx (main), /frontend/pages/ui/SatisfactionGauge.tsx (semicircle gauge with canvas needle), /frontend/pages/ui/FeedbackTable.tsx (scrollable table). All 5 sections + delay banner + filter row implemented. Uses sampleData + chartHelpers. No new packages needed — all done with Recharts + canvas API."
    },
    {
      "id": "phase-3",
      "title": "Demo Tracker Page: Kanban Board, Tables & Detail Drawer",
      "description": "Build /frontend/pages/TrackerPage.tsx — the operational tracking view.\n\nFilters: same Month/Geo/Type selectors as KPI page. Also a search box for organization name.\n\n⚠️ DELAY FLAG SECTION: At top, show a dismissible alert banner listing how many demos are delayed (lead_days < 3 and status not Canceled). Each flagged demo shown as a chip that scrolls to it.\n\nSection 1 — Demo Pipeline Kanban Board:\nThree columns: 'Needs Review' (amber header), 'Reviewed' (green header), 'Cancelled' (red header).\nEach column has count badge and scrollable card list (max height 500px).\nKanban cards are compact agenda-style:\n- Top row: organization name (bold) + geo badge (right)\n- Bottom row: date (left) + READY badge if readiness_date exists + demo type (right)\n- If slack_link: small '# Open in Slack' button\n- If lead_days < 3: show DELAYED chip in red on card\nClicking a card opens a right-side drawer panel.\n\nDetail Drawer (sheet from right, 460px wide):\n- Status/Type/Geo badges row\n- If delayed: red alert banner 'DELAYED — only X days lead time'\n- When section\n- Who section\n- Where section  \n- What section\n- Links section (Slack anchor if exists)\n- Lead Time bar (visual progress bar colored by band)\n- 'Mark as Ready' button (sets readiness_date to today's date in state)\n- If already ready: 'Ready — Marked DD-MM-YYYY' green chip\n\nSection 2 — Readiness Table (collapsible):\nShows upcoming non-cancelled demos sorted by date.\nColumns: Demo Date, Type, Organization, Geo, Host, Lead Days (with DelayBadge), Requester, Date of Readiness.\nRows with lead_days < 3 are highlighted with left red border (delayed flag).\n\nSection 3 — Completed Demos Table (collapsible):\nPast reviewed demos. Columns: Date, Type, Organization, Guests, Geo, Host, Lead Days, Requester, Date of Readiness.\n\nSection 4 — Cancelled Table (collapsible):\nColumns: Date, Geo, Type, Requester, Organization, Cancel Reason.\n\nAll tables use TanStack Table with sorting, sticky headers, and row hover states.\n\nDelay logic: a demo is 'delayed' if lead_days is between 0-2 (inclusive) and status != Canceled. Show this consistently throughout the page with red indicators.",
      "status": "complete",
      "notes": "TrackerPage built across 3 files: /frontend/pages/TrackerPage.tsx (main page - filters, kanban, delay banner), /frontend/pages/ui/DemoDetailDrawer.tsx (Sheet drawer with lead-time bar + mark-ready), /frontend/pages/ui/TrackerTables.tsx (generic DataTable + 3 collapsible TanStack sections). Readiness overrides stored as Record<string,string> in TrackerPage state and passed down. isDelayed = lead_days < 3 && not Canceled/DELETED. Highlight-on-scroll implemented for delay banner chips. No new packages needed — uses existing @tanstack/react-table, shadcn Sheet/Collapsible/Table/Progress/Input/Select/Button, Lucide icons."
    },
    {
      "id": "phase-4",
      "title": "Demo Calendar Page + Post Demo Analytics Page",
      "description": "BUILD TWO PAGES:\n\n=== PAGE A: /frontend/pages/CalendarPage.tsx ===\n\nFilters: Status, Geo, Month selects.\n\nLayout: left calendar grid (70% width) + right agenda pane (30%).\n\nCalendar grid:\n- Weekday headers: Mon-Sun\n- Days grid: each cell shows day number + up to 3 event chips\n- Chip color: left border colored by status (green=Reviewed, orange=Needs Review, red=Cancelled)\n- Chip text: 'GEO | ORG_NAME | TYPE_SHORT'\n- Today highlighted with blue circle on date number\n- Selected day has blue border\n- Click day → shows agenda\n- Month nav: prev/next arrows + month label + Today button\n- Geo toggle buttons: UK/JP/US/DE flags\n\nAgenda pane:\n- Shows events for selected day sorted by start_time\n- Each agenda card: type label, time, geo badge, org name, status chip, READY tag if readiness_date exists\n- Clicking card opens same drawer as TrackerPage\n- Pending (no date) section at bottom\n\nBottom legend: Approved (green dot), Needs Review (orange), Cancelled (red).\n\n=== PAGE B: /frontend/pages/PostDemoPage.tsx ===\n\nFilters: Month, Geo, Type selects.\n\nKPI row (6 cards): Total Sessions, Total Interventions, Avg Int/Demo, Total Issues, Total UDs, Top Operator.\n\nTop grid (3 columns):\n- Geo Distribution donut\n- Demo Type Mix donut\n- Model Behavior Trends: Recharts AreaChart, x-axis=MM-DD dates, one area per top-5 behavior tag. Overlapped semi-transparent fills.\n\nRow 2 (3 columns):\n- Top Interventions: horizontal BarChart (indexAxis:y) showing top 8 intervention types by count. Red bars.\n- Driving Feature Performance: vertical BarChart per feature. Multi-color bars.\n- Vehicle Utilization: custom progress list (vehicle_id + session count + bar).\n\nAll Demo Sessions table (collapsible):\nColumns: Date, Geo, Vehicle, Model, Issues (red bold if any, italic muted 'No issues' if none), Issue Count (number_of_uds, red if >0), Interventions (summary), Intervention Count, Operator.\nMax 200 rows shown. TanStack Table with sorting.\n\nRow 4 (50/50 grid):\n- Left: Intervention Top Count table. Columns: #, Type, Count, Share bar. Red accent header.\n- Right: Model Utilization horizontal bar chart (aggregated model+aux_model counts). Green accent (#10B981).\n\nRow 5 (60/40 grid):\n- Left: Operators Per Runs horizontal bar chart. Show count labels at bar end. Orange accent (#F59E0B).\n- Right: Issue Breakdown horizontal bar chart (UI Crash, Power Cycle, Blue Light, UDs, GPS). Orange accent.",
      "status": "complete",
      "notes": "CalendarPage at /frontend/pages/CalendarPage.tsx: filter row (Status select + Month select + Geo toggle flags), left 70% calendar grid with Mon-Sun headers, colored left-border event chips (green/orange/red by status), today=blue circle, selected day=blue ring, month prev/next nav, agenda pane (30%) showing selected day events sorted by start_time + pending review section (Needs Review demos this month), DemoDetailDrawer integration with readiness overrides.\n\nPostDemoPage at /frontend/pages/PostDemoPage.tsx: Month/Geo/Type filter row, 6 KPI StatCards, Row1=Geo donut+Type donut+Behavior AreaChart (overlapping semi-transparent, top-5 categories), Row2=Top Interventions horizontal BarChart (red)+Feature Performance vertical BarChart (multi-color Cells)+Vehicle Utilization progress list, PostDemoSessions collapsible table (TanStack, 9 cols, sorting), Row4=Intervention Count table (red accent header + share bars)+Model Utilization horizontal bar (green), Row5=Operators Per Runs horizontal bar (orange, LabelList)+Issue Breakdown horizontal bar (orange).\n\nPostDemoSessions at /frontend/pages/ui/PostDemoSessions.tsx: collapsible TanStack table, 9 columns (Date, Geo, Vehicle, Model, Issues red-bold/italic-muted, UDs red if >0, Interventions summary, Int Count, Operator), sticky header, alternating rows, sort by demo_datetime desc by default."
    },
    {
      "id": "phase-5",
      "title": "Demo Cockpit Page + Demo Cost Page",
      "description": "BUILD TWO PAGES:\n\n=== PAGE A: /frontend/pages/CockpitPage.tsx ===\n\nHeader: Action Required badge (count of Needs Review demos, red pill with pulsing dot).\n\nFilters row:\n- Geo segmented filter: All/UK/US/DE/JP\n- Time segmented filter: All Time/This Week/Today/Tomorrow/Next Week\n\nView switcher (4 buttons): Table, Board, List, Split.\n\nSearch bar: Status dropdown (All/Planned/Complete/Needs Review/Canceled) + org search input.\n\nTABLE VIEW:\nTanStack Table. Columns: Status badge, Schedule (date + time range), Organisation, Geo flag, Demo Type, Request Date, Actions (shortcuts row: Slack icon, Calendar icon, Reschedule, Approve, Cancel, Edit buttons).\nRows with lead_days < 3 have yellow left border (delayed highlight).\nApprove button: changes status from Needs Review → Reviewed. Shows success toast.\nCancel button: opens dialog with reason selector (Client request, Vehicle unavailable, Driver unavailable, Route issue, Weather, Internal ops conflict, Safety concern, Other). On confirm: sets status to Canceled + stores reason.\nReschedule: opens dialog with date/time inputs. On confirm: updates demo_date, start_time, end_time in state.\nEdit: opens expand modal with all editable fields.\nPagination: 15 rows per page.\n\nBOARD VIEW:\n4 columns: Needs Review, Planned (Reviewed+future), Complete (Reviewed+past), Canceled.\nKanban cards same style as TrackerPage.\nDrag info text shown (no actual drag required, just visual).\nClicking card opens right side drawer with full detail.\n\nLIST VIEW:\nAccordion list. Each row: status badge + org name + date + type. Expanding shows full detail grid.\n\nSPLIT VIEW (Mailbox):\nLeft panel 320px: scrollable card list (status + org + date + geo).\nRight panel: full detail of selected record.\n\nAll mutations are optimistic (update local state immediately), show sonner toasts.\n\nDelay indicator: any demo with lead_days 1-2 shows 'DELAYED' red badge in all views.\n\n=== PAGE B: /frontend/pages/CostPage.tsx ===\n\nLayout: left form card + right preview card.\n\nLeft — Cost Form:\nHero box (gradient blue) showing: 'Estimated Total Cost' label + large formatted cost + summary line.\n\nForm fields:\n- Estimate Name text input\n- Region/Geo select (UK GBP / US USD / DE EUR)\n- Main Demo Vehicles number input\n- Add Backup Vehicle checkbox (reveals: Backup Distance km + Backup Work Hours)\n- Distance (km per vehicle)\n- Operators number\n- Leads number\n- Travel Hours (Total Duty Time)\n\nCost calculation logic (runs on every input change):\n- Rates by geo: UK={opHr:23, leadHr:28, kmCost:0.14, hotel:125, meal:65}, US={opHr:30, leadHr:36, kmCost:0.16, hotel:200, meal:85}, DE={opHr:25, leadHr:30, kmCost:0.15, hotel:140, meal:70}\n- totalDuty = travelH + 2\n- teamSize = ops + leads\n- needsHotel = travelH > 4 || totalDuty > 11 ? 1 : 0\n- meals = needsHotel ? 2 : (totalDuty > 6 ? 1 : 0)\n- staffCost = (ops * totalDuty * opHr) + (leads * totalDuty * leadHr)\n- logCost = (teamSize * needsHotel * hotel) + (teamSize * meals * meal)\n- fleetCost = vehicles * dist * kmCost\n- backupCost = hasBackup ? (backupH * opHr + backupDist * kmCost) : 0\n- grandTotal = staffCost + logCost + fleetCost + backupCost\n\nRight — Preview card:\nCost Breakdown list (Staff, Logistics, Fleet, Backup — only non-zero rows).\nTotal row at bottom.\n\nBelow preview: Recent Estimates table (in-memory state array). Columns: Name, Geo, Total. Load/Delete buttons.\nSave button: adds to in-memory estimates array with timestamp. Success toast.",
      "status": "complete",
      "notes": "CockpitPage at /frontend/pages/CockpitPage.tsx: Action Required pulsing badge (count of NR demos), Geo segmented filter (All/UK/US/DE/JP), Time segmented filter (All Time/This Week/Today/Tomorrow/Next Week), View switcher (Table/Board/List/Split), Status+org search bar. TABLE VIEW: TanStack Table 15/page, yellow left border for lead_days<3, Status+DELAYED badge in col, all 6 action buttons (Slack/Calendar icons + Reschedule/Approve/Cancel/Edit). BOARD VIEW: 4 Kanban columns (Needs Review/Planned/Complete/Canceled), click→DemoDetailDrawer sheet. LIST VIEW: shadcn Accordion with full detail on expand. SPLIT VIEW: 320px scrollable card list + inline DetailPanel right side. All mutations optimistic with sonner toasts. CancelDialog/RescheduleDialog/EditDialog in /frontend/pages/ui/CockpitDialogs.tsx.\n\nCostPage at /frontend/pages/CostPage.tsx: Gradient blue hero box showing live estimated total. Form fields: name, geo/currency select (UK/US/DE), vehicles, backup checkbox (reveals backupDist+backupH), dist, ops, leads, travelH. Live cost calc on every change using rate tables. Right preview: Staff/Logistics/Fleet/Backup breakdown + applied rates card + logistics trigger alert. Recent Estimates in-memory table with Load/Delete. Toaster added globally in App.tsx."
    },
    {
      "id": "gap-review",
      "title": "Review the conversion for gaps and queue fix phases",
      "description": "Review the completed target app against the source classic app under\n/context/linked-classic-app/. Identify conversion gaps, but do not fix them inline in\nthis phase.\n\nCompare the source and target app coverage for:\n- pages/routes\n- containers and widgets\n- queries, trigger behavior, and query parameters\n- event handlers\n- transformers, scripts, and state variables\n\nFor each material gap, append one focused fix phase with\n`extend_phased_build_plan`. Each appended phase should be self-contained and small\nenough for one context window.\n\nKeep any comparison notes private or in tool arguments only; do not narrate the full\naudit to the user. Do not re-queue gaps already covered by existing phases.\n\nWhen all identified gaps have been queued, call `complete_build_phase`. If no gaps\nare found, call `complete_build_phase` without appending phases.",
      "status": "complete",
      "notes": "Source classic app was empty (single Page 1, no widgets, no queries, empty Frame). No conversion gaps exist — target app is a complete greenfield build."
    }
  ]
}
